[
    {
        "ID": "4579F00804F94B54B23CF207856E495F",
        "Name": "Google Search Plus",
        "Description": "Plugin for searching Google and navigating directly to the search results.",
        "Author": "mikemorain",
        "Version": "1.0.3",
        "Language": "csharp",
        "Website": "https://github.com/jjw24/Wox.Plugin.GoogleSearch",
        "UrlDownload": "https://github.com/jjw24/Wox.Plugin.GoogleSearch/releases/download/v1.0.3/Wox.Plugin.GoogleSearch.zip",
        "UrlSourceCode": "https://github.com/jjw24/Wox.Plugin.GoogleSearch/tree/master",
        "ETag": "W/\"78be610bfe7a6b99d95d0f4c8c8f3a15e2a56d48bd5d321a504791353b4181bb\"",
        "IcoPath": "https://cdn.jsdelivr.net/gh/jjw24/Wox.Plugin.GoogleSearch@master/Wox.Plugin.GoogleSearch/images/icon.png"
    },
    {
        "ID": "176690627AB54C8381A7FD99A3519F42",
        "Name": "Plugin Runner",
        "Description": "Create simple command shortcuts",
        "Author": "Jesse Barocio (@jessebarocio)",
        "Version": "2.2.3",
        "Language": "csharp",
        "Website": "https://github.com/jjw24/Wox.Plugin.Runner",
        "UrlDownload": "https://github.com/jjw24/Wox.Plugin.Runner/releases/download/v2.2.3/Wox.Plugin.Runner.zip",
        "UrlSourceCode": "https://github.com/jjw24/Wox.Plugin.Runner/tree/master",
        "ETag": "W/\"f22db5ce34fdfcfe31df37b3bd26309d041de0e41f976e47c58c75547f8d5b47\"",
        "IcoPath": "https://cdn.jsdelivr.net/gh/jjw24/Wox.Plugin.Runner@master/Wox.Plugin.Runner/Images/gear.png"
    },
    {
        "ID": "c3406b5c-22f0-4984-b018-3dae897cab3f",
        "Name": "Dictionary",
        "Description": "English dictionary, word correction and synonym.",
        "Author": "Harry Yu",
        "Version": "2.2.3",
        "Language": "csharp",
        "Website": "https://github.com/harrynull/Flow.Launcher.Dictionary",
        "UrlDownload": "https://github.com/harrynull/Flow.Launcher.Dictionary/releases/download/v2.2.3/Dictionary.zip",
        "UrlSourceCode": "https://github.com/harrynull/Flow.Launcher.Dictionary/tree/main",
        "ETag": "W/\"5a2a8b2e492969788b8c352c30324e22837675c36d96c0cb75326e717baf4877\"",
        "IcoPath": "https://cdn.jsdelivr.net/gh/harrynull/Flow.Launcher.Dictionary@main/Images/plugin.png"
    },
    {
        "ID": "SY91U1N7H9D0X1DTZ8IOP4YV43KT7C5M",
        "Name": "SpotifyPremium",
        "Description": "Spotify Premium for Flow Launcher",
        "Author": "Frank W. (@fow5040)",
        "Version": "1.1.0",
        "Language": "csharp",
        "Website": "https://github.com/fow5040/Flow.Launcher.Plugin.SpotifyPremium",
        "UrlDownload": "https://github.com/fow5040/Flow.Launcher.Plugin.SpotifyPremium/releases/download/v1.1.0/Flow.Launcher.Plugin.SpotifyPremium.zip",
        "UrlSourceCode": "https://github.com/fow5040/Flow.Launcher.Plugin.SpotifyPremium/tree/main",
        "ETag": "W/\"c3bf530943cb3f7c7e484af52e4fe6371d3f273ccaf84126aeabcfb2c7a4526a\"",
        "IcoPath": "https://cdn.jsdelivr.net/gh/fow5040/Flow.Launcher.Plugin.SpotifyPremium@main/icon.png"
    },
    {
        "ID": "8025ce8b-b1ce-49cd-af48-b343a0df8606",
        "Name": "Clipboard History",
        "Description": "a Clipboard History Plugin for FlowLauncher",
        "Author": "liberize,Xenolphthalein",
        "Version": "1.1.1",
        "Language": "csharp",
        "Website": "https://github.com/liberize/Flow.Launcher.Plugin.ClipboardHistory",
        "UrlDownload": "https://github.com/liberize/Flow.Launcher.Plugin.ClipboardHistory/releases/download/v1.1.1/ClipboardHistory-1.1.1.zip",
        "UrlSourceCode": "https://github.com/liberize/Flow.Launcher.Plugin.ClipboardHistory/tree/master",
        "ETag": "W/\"14b61a01d827c1d27b4d36e671109f642e77e1dc47853fc44cb74af366aeb007\"",
        "IcoPath": "https://cdn.jsdelivr.net/gh/liberize/Flow.Launcher.Plugin.ClipboardHistory@master/Images/clipboard.png"
    },
    {
        "ID": "F737A9223560B3C6833B5FFB8CDF78E5",
        "Name": "Window Walker",
        "Description": "Alt-Tab alternative enabling searching through your windows.",
        "Author": "betadele",
        "Version": "2.0.1",
        "Language": "csharp",
        "Website": "https://www.windowwalker.com/",
        "UrlDownload": "https://github.com/taooceros/Microsoft.Plugin.WindowWalker/releases/download/v2.0.1/WindowWalker-2.0.1.zip",
        "UrlSourceCode": "https://github.com/taooceros/Microsoft.Plugin.WindowWalker/tree/master",
        "ETag": "W/\"14d95e9aa492f8f02edfd38f28db2fd4d7962e253d9ea69751d1ad75046f4e96\"",
        "IcoPath": "https://cdn.jsdelivr.net/gh/taooceros/Microsoft.Plugin.WindowWalker@master/Images/windowwalker.dark.png"
    },
    {
        "ID": "D2D2C23B084D411DB66FE0C79D6C2A6E",
        "Name": "Everything",
        "Description": "Search Everything",
        "Author": "qianlifeng, orzfly",
        "Version": "1.5.6",
        "Language": "csharp",
        "Website": "https://github.com/Flow-Launcher/Flow.Launcher.Plugin.Everything",
        "UrlDownload": "https://github.com/Flow-Launcher/Flow.Launcher.Plugin.Everything/releases/download/v1.5.6/Flow.Launcher.Plugin.Everything.zip",
        "UrlSourceCode": "https://github.com/Flow-Launcher/Flow.Launcher.Plugin.Everything/tree/master",
        "ETag": "W/\"ec4574beeaee8cf78f45abbf356eb4a813b45c54abeaeedfa73a52bec47d556c\"",
        "IcoPath": "https://cdn.jsdelivr.net/gh/Flow-Launcher/Flow.Launcher.Plugin.Everything@master/Images/find.png"
    },
    {
        "ID": "9B36CE6181FC47FBB597AA2C29CD9B0A",
        "Name": "Colors",
        "Description": "Provides HEX and RGB color preview.",
        "Author": "qianlifeng, Vladimir Antos, bluray",
        "Version": "2.0.1",
        "Language": "csharp",
        "Website": "https://github.com/Flow-Launcher/Flow.Launcher.Plugin.Color",
        "UrlDownload": "https://github.com/Flow-Launcher/Flow.Launcher.Plugin.Color/releases/download/v2.0.1/Color-2.0.1.zip",
        "UrlSourceCode": "https://github.com/Flow-Launcher/Flow.Launcher.Plugin.Color/tree/main",
        "ETag": "W/\"d0a5b564efd23e022e16eaf780e462cc6c1a9576fe33d3d2ed4aa98de7ba479b\"",
        "IcoPath": "https://cdn.jsdelivr.net/gh/Flow-Launcher/Flow.Launcher.Plugin.Color@main/Images/color.png"
    },
    {
        "ID": "18892B7863AC43ABA27859A5A2866DD8",
        "Name": "Currency Converter",
        "Description": "Currency converter using the euro and rates at https://www.ecb.europa.eu/",
        "Author": "deefrawley",
        "Version": "1.2.2",
        "Language": "python",
        "Website": "https://github.com/deefrawley/Flow.Launcher.Plugin.Currency",
        "UrlDownload": "https://github.com/deefrawley/Flow.Launcher.Plugin.Currency/releases/download/v1.2.2/Flow.Launcher.Plugin.Currency.zip",
        "UrlSourceCode": "https://github.com/deefrawley/Flow.Launcher.Plugin.Currency/tree/main",
        "ETag": "W/\"5a6d97b908d6cc32f18b5dae944e7f4600f0d9e39e68d385f48ac8fbb3b42240\"",
        "IcoPath": "https://cdn.jsdelivr.net/gh/deefrawley/Flow.Launcher.Plugin.Currency@main/assets/favicon.ico",
        "Tested": false
    },
    {
        "ID": "E2D2C23B084D41D1B6F60EC79D62CAH6",
        "Name": "IP Address",
        "Description": "Shows your internal and external IP address",
        "Author": "ishu3101",
        "Version": "1.2.1",
        "Language": "csharp",
        "Website": "https://github.com/taooceros/Flow.Plugin.IPAddress",
        "UrlDownload": "https://github.com/taooceros/Flow.Plugin.IPAddress/releases/download/v1.2.1/Flow.Plugin.IPAddress.zip",
        "UrlSourceCode": "https://github.com/taooceros/Flow.Plugin.IPAddress",
        "ETag": "W/\"12c553be75048941916578d3559cdd580635be0fea101cbd018a1d3499fd8d84\"",
        "IcoPath": "https://cdn.jsdelivr.net/gh/taooceros/Flow.Plugin.IPAddress@master/ipaddress.png"
    },
    {
        "ID": "D2D2C23B084D411DB66EE0C79D6C2A7C",
        "Name": "Flow.Plugin.UrlEncode",
        "Description": "urlencode or urldecode a string",
        "Author": "cxfksword",
        "Version": "1.0",
        "Language": "csharp",
        "Website": "https://github.com/cxfksword/Wox.Plugin.UrlEncode",
        "UrlDownload": "https://github.com/taooceros/Flow.Plugin.UrlEncode/releases/download/v1.0/Flow.Plugin.UrlEncode.zip",
        "UrlSourceCode": "https://github.com/taooceros/Flow.Plugin.UrlEncode",
        "ETag": "W/\"069f5b6c1d7a15adaa071192f554b0165ed0dc2b83d0895c5df4eab20a7f3178\"",
        "IcoPath": "https://cdn.jsdelivr.net/gh/taooceros/Flow.Plugin.UrlEncode@master/Images/app.png"
    },
    {
        "ID": "54A6672C06E047A48A7D88C78FA5F13E",
        "Name": "Putty",
        "Description": "Launch Putty Sessions",
        "Author": "Konstantin Zaitcev, Kai Eichinger (@cH40zLord)",
        "Version": "2.1.3",
        "Language": "csharp",
        "Website": "https://github.com/jjw24/Flow.Launcher.Plugin.Putty",
        "UrlDownload": "https://github.com/jjw24/Flow.Launcher.Plugin.Putty/releases/download/v2.1.3/Flow.Launcher.Plugin.Putty.zip",
        "UrlSourceCode": "https://github.com/jjw24/Flow.Launcher.Plugin.Putty/tree/master",
        "ETag": "W/\"88dab10fd68eb19cdf35541c8ce894fdf481356e85bc3dc95353c3f9f8d81c62\"",
        "IcoPath": "https://cdn.jsdelivr.net/gh/jjw24/Flow.Launcher.Plugin.Putty@master/Flow.Launcher.Plugin.Putty/icon.png"
    },
    {
        "ID": "81b8c8c8-72ef-427c-a9c1-17cf8f1c766c",
        "Name": "LibreTranslate",
        "Description": "a translation plugin for Flow-Launcher",
        "Author": "taooceros",
        "Version": "1.0.1",
        "Language": "csharp",
        "Website": "https://github.com/taooceros/Flow.LibreTranslate",
        "UrlDownload": "https://github.com/taooceros/Flow.LibreTranslate/releases/download/v1.0.1/Flow.LibreTranslate.zip",
        "UrlSourceCode": "https://github.com/taooceros/Flow.LibreTranslate/tree/main",
        "ETag": "W/\"7fee694ad9dd969f94f430ab07801862c0ca41217bfe5a1f6b4babc9ef7e47f8\"",
        "IcoPath": "https://cdn.jsdelivr.net/gh/taooceros/Flow.LibreTranslate@main/Flow.LibreTranslate/Images//pic.png"
    },
    {
        "ID": "F71F6EE367D34BAFB681A9287ACF59EB",
        "Name": "Todoist",
        "Description": "A plugin to add tasks to todoist.",
        "Author": "DanielBV",
        "Version": "2.0.0",
        "Language": "csharp",
        "Website": "https://github.com/jjw24/Wox.Plugin.Todoist",
        "UrlDownload": "https://github.com/jjw24/Wox.Plugin.Todoist/releases/download/v2.0.0/Wox.Plugin.Todoist.zip",
        "UrlSourceCode": "https://github.com/jjw24/Wox.Plugin.Todoist/tree/master",
        "ETag": "W/\"c2b12673cffdb412beed8ea6db7f83205a09791a848cceb3586903d96b74815d\"",
        "IcoPath": "https://cdn.jsdelivr.net/gh/jjw24/Wox.Plugin.Todoist@master/src/images/icon.png"
    },
    {
        "ID": "5B7E53D506844D2D8B7001AA19F5EF8F",
        "Name": "Todos",
        "Description": "A simple todo app.",
        "Author": "caoyue",
        "Version": "2.0.1",
        "Language": "csharp",
        "Website": "https://github.com/jjw24/Wox.Plugin.Todos",
        "UrlDownload": "https://github.com/jjw24/Wox.Plugin.Todos/releases/download/v2.0.1/Wox.Plugin.Todos.zip",
        "UrlSourceCode": "https://github.com/jjw24/Wox.Plugin.Todos/tree/master",
        "ETag": "W/\"26676724274b95cf9c80f71e0589100b4e4dfb90c0763abb6422249d26a5eb6a\"",
        "IcoPath": "https://cdn.jsdelivr.net/gh/jjw24/Wox.Plugin.Todos@master/ico/app.png"
    },
    {
        "ID": "1b7c732781f94b748ed08351f8200894",
        "Name": "Direct Translate",
        "Description": "Translate between any languages supported by textblob.",
        "Author": "Drimix20",
        "Version": "2.0.0",
        "Language": "python",
        "Website": "https://github.com/Drimix20/Flow.Launcher.Plugin.DirectTranslate",
        "UrlDownload": "https://github.com/Drimix20/Flow.Launcher.Plugin.DirectTranslate/releases/download/2.0.0/Flow.Launcher.Plugin.DirectTranslate-2.0.0.zip",
        "UrlSourceCode": "https://github.com/Drimix20/Flow.Launcher.Plugin.DirectTranslate/tree/master",
        "ETag": "W/\"2b3e0c446be8bbc782cb45a3045197b7a88438a70816738db3e979198b8c9bf1\"",
        "IcoPath": "https://cdn.jsdelivr.net/gh/Drimix20/Flow.Launcher.Plugin.DirectTranslate@master/Images/app.png",
        "Tested": false
    },
    {
        "ID": "6c22cffe6b3546ec9087abe149c4a575",
        "Name": "GitHub",
        "Description": "Search Github repositories and users, browse issues and PRs",
        "Author": "Ioannis G. (@JohnTheGr8)",
        "Version": "1.2.2",
        "Language": "fsharp",
        "Website": "https://github.com/JohnTheGr8/Flow.Plugin.Github",
        "UrlDownload": "https://github.com/JohnTheGr8/Flow.Plugin.Github/releases/download/v1.2.2/Flow.Plugin.Github.zip",
        "UrlSourceCode": "https://github.com/JohnTheGr8/Flow.Plugin.Github/tree/main",
        "ETag": "W/\"c79e3fba76fd502b124cdeb181ca1abebc3dca2aa639d97911a9d02e8cdbcf23\"",
        "IcoPath": "https://cdn.jsdelivr.net/gh/JohnTheGr8/Flow.Plugin.Github@main/src/icon.png"
    },
    {
        "ID": "b9aaddfa36a948f384b31b4fb6186861",
        "Name": "isPrime",
        "Description": "Checks if the given arguments are prime numbers",
        "Author": "lvonkacsoh",
        "Version": "1.3.0",
        "Language": "python",
        "Website": "https://github.com/lvonkacsoh/Flow.Launcher.Plugin.IsPrime",
        "UrlDownload": "https://github.com/lvonkacsoh/Flow.Launcher.Plugin.IsPrime/releases/download/v1.3.0/Flow.Launcher.Plugin.IsPrime.zip",
        "UrlSourceCode": "https://github.com/lvonkacsoh/Flow.Launcher.Plugin.IsPrime/tree/main",
        "ETag": "W/\"f6ddbfbc56c9aec5b7947ab28c8e8211632340a7133b0bb0c29f7c2aea42f77c\"",
        "IcoPath": "https://cdn.jsdelivr.net/gh/lvonkacsoh/Flow.Launcher.Plugin.IsPrime@main/assets/icon.png",
        "Tested": false
    },
    {
        "ID": "5403b2dc28fb4327aedc9f8c872d9d1f",
        "Name": "RollDice",
        "Description": "Rolls the given dices and evaluates the expression",
        "Author": "lvonkacsoh",
        "Version": "1.0",
        "Language": "python",
        "Website": "https://github.com/lvonkacsoh/Flow.Launcher.RollDice",
        "UrlDownload": "https://github.com/lvonkacsoh/Flow.Launcher.RollDice/releases/download/v1.0/Flow.Launcher.RollDice.zip",
        "UrlSourceCode": "https://github.com/lvonkacsoh/Flow.Launcher.RollDice/tree/main",
        "ETag": "W/\"4c6534e263fcbafe6658266e2a9c68bb08a3f38c11b3ae830c951971c3da3064\"",
        "IcoPath": "https://cdn.jsdelivr.net/gh/lvonkacsoh/Flow.Launcher.RollDice@main/assets/icon.jpg",
        "Tested": false
    },
    {
        "ID": "FF2C31D6A47348FFB9ED4EB26F6794E2",
        "Name": "Fancy Emoji",
        "Description": "Search for emoji and add to your clipboard automatically",
        "Author": "Mave",
        "Version": "1.0.1",
        "Language": "python",
        "Website": "https://github.com/Ma-ve/Flow.Launcher.Plugin.FancyEmoji",
        "UrlDownload": "https://github.com/Ma-ve/Flow.Launcher.Plugin.FancyEmoji/releases/download/1.0.1/Flow.Launcher.Plugin.FancyEmoji.zip",
        "UrlSourceCode": "https://github.com/Ma-ve/Flow.Launcher.Plugin.FancyEmoji/tree/master",
        "Etag": "W/\"dfe66c7a7a2dd4c57d8b361135a6c042b25cc1e49d7ad4b9f966300d227ca65c\"",
        "IcoPath": "https://cdn.jsdelivr.net/gh/Ma-ve/Flow.Launcher.Plugin.FancyEmoji@master/icon.png",
        "Tested": false
    },
    {
        "ID": "84ddc2a6d43911e8a8d5f2801f1b9fd1",
        "Name": "Timestamp",
        "Description": "Show system time and could copy that",
        "Author": "Zero <Zeroto521>",
        "Version": "1.0.7",
        "Language": "python",
        "Website": "https://github.com/Zeroto521/Flow.Launcher.Plugin.Timestamp",
        "UrlDownload": "https://github.com/Zeroto521/Flow.Launcher.Plugin.Timestamp/archive/refs/heads/master.zip",
        "UrlSourceCode": "https://github.com/Zeroto521/Flow.Launcher.Plugin.Timestamp",
        "IcoPath": "https://cdn.jsdelivr.net/gh/Zeroto521/Flow.Launcher.Plugin.Timestamp@master/assets/favicon.ico",
        "Tested": false
    },
    {
        "ID": "73f2c04d-176a-4586-9ff5-69fae63321ef",
        "Name": "General Converter",
        "Description": "General weights and measures converter",
        "Author": "deefrawley",
        "Version": "1.1.1",
        "Language": "python",
        "Website": "https://github.com/deefrawley/Flow.Launcher.Plugin.GenConvert",
        "UrlDownload": "https://github.com/deefrawley/Flow.Launcher.Plugin.GenConvert/releases/download/v1.1.1/Flow.Launcher.Plugin.GenConvert.zip",
        "UrlSourceCode": "https://github.com/deefrawley/Flow.Launcher.Plugin.GenConvert/tree/main",
        "ETag": "W/\"04112b150f7ea0d4193f1c6f90e89ec4f6db5d64476c329b4aca220e0f8c32c6\"",
        "IcoPath": "https://cdn.jsdelivr.net/gh/deefrawley/Flow.Launcher.Plugin.GenConvert@main/assets/favicon.ico",
        "Tested": false
    },
    {
        "ID": "B2D2C23B055D411GH66FF0C79D6C2A6H",
        "Name": "HA-Commander",
        "Description": "Search, and interact with Home Assistant using Wox or Flow Launcher.",
        "Author": "Garulf",
        "Version": "2.5.0",
        "Language": "python",
        "Website": "https://github.com/Garulf/HA-Commander",
        "UrlDownload": "https://github.com/Garulf/HA-Commander/releases/download/v2.5.0/HA-Commander.zip",
        "UrlSourceCode": "https://github.com/Garulf/HA-Commander/tree/main",
        "ETag": "W/\"02c70196bf469f84c28b91886fe16cf7fde1d7b0b2aa0fa41a564e28e0467dc8\"",
        "IcoPath": "https://cdn.jsdelivr.net/gh/Garulf/HA-Commander@main/icons/home-assistant.png",
        "Tested": false
    },
    {
        "ID": "28b1bc8d-06e1-4bda-8311-f36e8d4f9915",
        "Name": "CPPreference",
        "Description": "Search cppreference.com efficiently",
        "Author": "Peter Schussheim",
        "Version": "1.0.1",
        "Language": "csharp",
        "Website": "https://github.com/peterschussheim/CPPreference-flow-plugin",
        "UrlDownload": "https://github.com/peterschussheim/CPPreference-flow-plugin/releases/download/v1.0.1/Flow.Launcher.Plugin.CPPreference.zip",
        "UrlSourceCode": "https://github.com/peterschussheim/CPPreference-flow-plugin/tree/master",
        "ETag": "W/\"0533c7551ccf50281f97a9809a768b36416c455a118380e7adbba2474cefa104\"",
        "IcoPath": "https://cdn.jsdelivr.net/gh/peterschussheim/CPPreference-flow-plugin@master/Flow.Launcher.Plugin.CPPreference/icon.png"
    },
    {
        "ID": "8G5CDC9A78EF4A7E667E138F1FC04015",
        "ActionKeyword": "mdi",
        "Name": "Search-MDI",
        "Description": "Search materialdesignicons.com",
        "Author": "Garulf",
        "Version": "2.2.6",
        "Language": "python",
        "Website": "https://github.com/Garulf/Search-MDI",
        "UrlDownload": "https://github.com/Garulf/Search-MDI/releases/download/v2.2.6/Search-MDI.zip",
        "UrlSourceCode": "https://github.com/Garulf/Search-MDI/tree/main",
        "ETag": "W/\"f15f627dfcc7dedbd3ae896c0b7e02a67d4e8edd803a4a4aec1cc584962b3c58\"",
        "IcoPath": "https://cdn.jsdelivr.net/gh/Garulf/Search-MDI@main/app.png",
        "Tested": false
    },
    {
        "ID": "32D9F15C38EE400EA7E3DF57DA15BFD5",
        "Name": "Plexy",
        "Description": "Search and cast your Plex Media Server Library",
        "Author": "Garulf",
        "Version": "0.5.2",
        "Language": "python",
        "Website": "https://github.com/Garulf/plexy",
        "UrlDownload": "https://github.com/Garulf/Plexy/releases/download/v0.5.2/Plexy.zip",
        "UrlSourceCode": "https://github.com/Garulf/plexy/tree/main",
        "ETag": "W/\"fcfee8a945f8db281013aa9f20c0c3b253bb80b3855cb894fe2f894452cacd27\"",
        "IcoPath": "https://cdn.jsdelivr.net/gh/Garulf/plexy@main/./icons/plex.png",
        "Tested": false
    },
    {
        "ID": "4D5DF575E4964C6AAADCF86134F09CC0",
        "Name": "Steam Search",
        "Description": "Search and launch your Steam Game library",
        "Author": "Garulf",
        "Version": "1.2.0",
        "Language": "python",
        "Website": "https://github.com/Garulf/Steam-Search",
        "UrlDownload": "https://github.com/Garulf/Steam-Search/releases/download/v1.2.0/Steam-Search.zip",
        "UrlSourceCode": "https://github.com/Garulf/Steam-Search/tree/main",
        "ETag": "W/\"5140bc2c209b186f108ce75350633d49415f373906f0ee032afba259f04ac5b7\"",
        "IcoPath": "https://cdn.jsdelivr.net/gh/Garulf/Steam-Search@main/plugin/icon/steam-icon.png",
        "Tested": false
    },
    {
        "ID": "477F16413D374364A4D5D36DCE68ED45",
        "Name": "Twitchy",
        "Description": "Search and stream twitch.tv",
        "Author": "Garulf",
        "Version": "1.1.0",
        "Language": "python",
        "Website": "https://github.com/Garulf/twitchy",
        "UrlDownload": "https://github.com/Garulf/twitchy/releases/download/v1.1.0/twitchy.zip",
        "UrlSourceCode": "https://github.com/Garulf/twitchy/tree/main",
        "ETag": "W/\"f0cc7f84c7cc6d307fce49081d6eadcb0671a6d1dd78059775c5a3795881bd08\"",
        "IcoPath": "https://cdn.jsdelivr.net/gh/Garulf/twitchy@main/icon.png",
        "Tested": false
    },
    {
        "ID": "095A6AE3A255532EAAD78F05A71D4981",
        "Name": "Quick Uninstaller",
        "Description": "A plugin for uninstalling programs",
        "Author": "Hogan Lee",
        "Version": "2.0.0",
        "Language": "CSharp",
        "Website": "https://github.com/jjw24/Wox.Plugin.QuickUninstaller",
        "UrlDownload": "https://github.com/jjw24/Wox.Plugin.QuickUninstaller/releases/download/v2.0.0/QuickUninstaller.zip",
        "UrlSourceCode": "https://github.com/jjw24/Wox.Plugin.QuickUninstaller/tree/master",
        "ETag": "W/\"d656e1cffe62575c372276b5f1cdb0b4ad10385155976cc9c7499474aa021647\"",
        "IcoPath": "https://cdn.jsdelivr.net/gh/jjw24/Wox.Plugin.QuickUninstaller@master/QuickUninstaller/Images/UninstallerIcon.png"
    },
    {
        "ID": "3C62514E3C8644D583E3F12202F11161",
        "Name": "nexusmods-search",
        "Description": "Search Nexusmods.com",
        "Author": "Garulf",
        "Version": "0.2.1",
        "Language": "python",
        "Website": "https://github.com/Garulf/nexusmods-search",
        "UrlDownload": "https://github.com/Garulf/Nexusmods-Search/releases/download/v0.2.1/Nexusmods-Search.zip",
        "UrlSourceCode": "https://github.com/Garulf/nexusmods-search/tree/main",
        "ETag": "W/\"f410b818918d0ed79bf21f1a08673e694e292fa3a6063bbae1c2d79ca483d362\"",
        "IcoPath": "https://cdn.jsdelivr.net/gh/Garulf/nexusmods-search@main/./icon.png",
        "Tested": false
    },
    {
        "ID": "D0DB38F5-0199-4DFC-8A8D-1B22F68C157C",
        "ActionKeyword": "*",
        "Name": "Favorites",
        "Description": "Flow Launcher plugin to define favorite apps, files, folders and URLs.",
        "Author": "stax76",
        "Version": "1.3",
        "Language": "csharp",
        "Website": "https://github.com/stax76/Flow.Launcher.Plugin.Favorites",
        "UrlDownload": "https://github.com/stax76/Flow.Launcher.Plugin.Favorites/releases/download/v1.3/Flow.Launcher.Plugin.Favorites-v1.3.zip",
        "UrlSourceCode": "https://github.com/stax76/Flow.Launcher.Plugin.Favorites/tree/master",
        "IcoPath": "https://raw.githubusercontent.com/stax76/Flow.Launcher.Plugin.Favorites/master/Icons/Web.ico",
        "ETag": "W/\"281a24bbb5c5b17b066829b3f8db59c9d2ce29da3e93eb73b3e4ead801f61966\""
    },
    {
        "ID": "d6675ca0-9da6-4361-8342-95564214cd04",
        "Name": "Number Converter",
        "Description": "Convert numbers between dec/oct/hex/bin",
        "Author": "liberize",
        "Version": "1.0.0",
        "Language": "python",
        "Website": "https://github.com/liberize/Flow.Launcher.Plugin.NumberConverter",
        "UrlDownload": "https://github.com/liberize/Flow.Launcher.Plugin.NumberConverter/releases/download/v1.0.0/NumberConverter-1.0.0.zip",
        "UrlSourceCode": "https://github.com/liberize/Flow.Launcher.Plugin.NumberConverter/tree/main",
        "IcoPath": "https://cdn.jsdelivr.net/gh/liberize/Flow.Launcher.Plugin.NumberConverter@main/Images/app.png",
        "ETag": "W/\"6086dbaac6acbd24c66318643697ae6a9a4337e4d7260f6f3561b857ad847c52\"",
        "Tested": false
    },
    {
        "ID": "C7E78C47FA5942E4B7972EAD844F5007",
        "Name": "Window Services",
        "Description": "Start and stop Windows services.",
        "Author": "Garulf",
        "Version": "1.1.1",
        "Language": "python",
        "Website": "https://github.com/Garulf/window-services",
        "UrlDownload": "https://github.com/Garulf/window-services/releases/download/v1.1.1/window-services.zip",
        "UrlSourceCode": "https://github.com/Garulf/window-services/tree/main",
        "IcoPath": "https://github.com/Garulf/window-services/raw/c78cdb4b51c62fb09d860dad143c8773c686c967/icons/cog.png",
        "ETag": "W/\"99c8765cc3c37b428cadc7edb828c0a62a29cd392812eac00bc9e4a1b9de099d\"",
        "Tested": false
    },
    {
        "ID": "4F31D5DF26984581BDF4213D40860ADF",
        "Name": "Windows Dark Mode Toggle",
        "Description": "Toggle Window's Dark & Light modes",
        "Author": "Garulf",
        "Version": "1.0.0",
        "Language": "python",
        "Website": "https://github.com/Garulf/windows-dark-mode-toggle",
        "UrlDownload": "https://github.com/Garulf/windows-dark-mode-toggle/releases/download/v1.0.0/windows-dark-mode-toggle.zip",
        "UrlSourceCode": "https://github.com/Garulf/windows-dark-mode-toggle/tree/main",
        "IcoPath": "https://github.com/Garulf/windows-dark-mode-toggle/raw/main/icon/light-dark.png",
        "ETag": "W/\"bd1df1f3d532bd1427c2689e138732f12dad44b1624a28ff6819191715ffa562\"",
        "Tested": false
    },
    {
        "ID": "747F1A93B6D24CCFBC433BA2455B3BEA",
        "Name": "Windows Startup",
        "Description": "Control Windows start-up programs.",
        "Author": "Garulf",
        "Version": "1.0.1",
        "Language": "python",
        "Website": "https://github.com/Garulf/Windows-Startup",
        "UrlDownload": "https://github.com/Garulf/Windows-Startup/releases/download/v1.0.1/Windows-Startup.zip",
        "UrlSourceCode": "https://github.com/Garulf/Windows-Startup/tree/main",
        "IcoPath": "https://github.com/Garulf/Windows-Startup/raw/main/icons/application.png",
        "ETag": "W/\"2176750efccce710c2175c47815133bdeadcc8cc86be4025f9605b2c4e240721\""
    }
]